synopsis/__init__.py
synopsis/synopsis.py
topicfinder/__init__.py
topicfinder/topicfinder.py
topicfinder-0.1.1.dist-info/LICENSE
topicfinder-0.1.1.dist-info/METADATA
topicfinder-0.1.1.dist-info/WHEEL
topicfinder-0.1.1.dist-info/top_level.txt
topicfinder-0.1.1.dist-info/RECORD
