Metadata-Version: 2.1
Name: topicfinder
Version: 0.1.1
Summary: finding topics in a set of documents in an unsupervised fashion.
Home-page: https://gitlab.com/gracekatherineturner/synopsis
Author: Grace Turner
Author-email: gracekatherineturner@gmail.com
License: UNKNOWN
Project-URL: Bug Tracker, https://gitlab.com/gracekatherineturner/synopsis
Platform: UNKNOWN
Classifier: Programming Language :: Python :: 3
Classifier: License :: OSI Approved :: MIT License
Classifier: Operating System :: OS Independent
Requires-Python: >=3.6
